{
    "X2ySEYZ32iA": 1,
    "xvHhdY6Ma1c": 1,
    "pTvU0kV6PdM": 1,
    "PDeTO26fRVQ": 1,
    "G7eL0tX7vDg": 1,
    "HpYdA-06jTc": 1,
    "gqhWHy0rrtM": 1,
    "Z8_X2rc0ZHU": 2,
    "vj51TWvOWYk": 1,
    "kJOD4D44BJU": 1,
    "TV7HOGNXybU": 2,
    "c6K-ZVVaspE": 1,
    "qJIfavKyYvU": 1,
    "n0cJyrkmVQY": 1,
    "J9YhjsvySwQ": 1,
    "1j1NjXTcjM4": 2,
    "n0UKngJuPas": 1,
    "LrWZmurjikM": 1,
    "aXhYOCs8ViM": 1,
    "-1CwZ-U7UEs": 1,
    "4f6Mr4NVKuY": 1,
    "n8ivrvrhIBk": 1,
    "Z0aL27J0OYU": 1,
    "lHgtB7DuOD8": 1,
    "ttWgjaGYR80": 1,
    "sEqXuSl1JeE": 1,
    "RT8lcTEqY4s": 1,
    "_n8XQt14Hq4": 1,
    "wewKUu0-XpU": 1,
    "u78TKRPM-hQ": 1,
    "FL6aDkidnR4": 1,
    "ZiMIC3_NBC8": 1,
    "_lDL7eynJN4": 1,
    "BeBZ6RTzoCg": 1,
    "E8BYlzBkegI": 1,
    "g5xjSfApp6M": 1,
    "yue4cjkayKc": 1,
    "uJuSMlZ9si4": 1,
    "MRGlXlLeOe8": 1,
    "dOrRSCJ2Z8c": 1,
    "HF40KVcBrSo": 1,
    "ZXEC0IrOWGk": 1,
    "wZh4vIFJqOg": 1,
    "X0AbG4-k3Ak": 1,
    "ytNqxjuuJQY": 1,
    "Lp9GodIuPaY": 1,
    "ttDlTDd2VEY": 1,
    "wslUaFy7fHk": 1,
    "9mTYo1ztLuE": 1,
    "7mFvyrNHZRY": 1,
    "HthdTdvAQQc": 1,
    "I63RkFdgjos": 1,
    "riQI-wqRfCw": 1,
    "iSallxKpm8Y": 1,
    "RCuXq9v2UYg": 1,
    "6E-_CZf85mA": 1,
    "elKgsfGDenA": 1,
    "XEPMlLCL8-I": 1,
    "_l76TEQ8r9c": 1,
    "8JtNwQTKCSs": 1,
    "27Uad0mScoQ": 1,
    "92Q-X2AbnGw": 1,
    "B85PyaWFOV8": 2,
    "Gwg_KYNgu6Y": 1,
    "m9ezpAUvMC8": 3,
    "2N_yEqbYY0Y": 1,
    "9jG_62R3seQ": 1,
    "xtDQF0J6NjY": 2,
    "RkkdYdWMfQ0": 1,
    "iAdvF-aYb8Q": 1,
    "vtnlZJlj2t4": 1,
    "GgkiKThnTDU": 1,
    "mDtsA8xCI98": 1,
    "RNexLnjf-eI": 1,
    "WJF5Z1WRcqw": 2,
    "2CuQhaaoqZM": 2,
    "tlEAEJKIatc": 2,
    "ANXUyLBD3E4": 3,
    "oewANcF6hVY": 1,
    "uo2tnJM960c": 1,
    "w-ODm6AUayE": 1,
    "gDyGtltN6LQ": 1,
    "eDWzGAspSvM": 3,
    "JQev5LfT8uA": 3,
    "6lxBcKB3Ohc": 1,
    "7RVhnmUdf2c": 1,
    "TbJPfXorPkk": 1,
    "9Cp-hNvSWZs": 1,
    "EoJLlOhUo-M": 1,
    "PVQ_hcd_DUc": 1,
    "7OA28i5HJhw": 1,
    "epm7tAtEvYA": 1,
    "t8Z2qM07Ugg": 1,
    "rLR37BR88T0": 1,
    "1-Z6bd7SRBA": 1,
    "K_gHvUWtPvE": 1,
    "3U2dNKBM28o": 1,
    "lfz4Lefac1Y": 1,
    "2R6iKxc9ACc": 1,
    "lCD0Qmm3MA0": 1,
    "Mg6z-Om-3J0": 1,
    "GLWnRSrB4PM": 1,
    "o8XRrqQOjI0": 1,
    "dYu1hHy1NX4": 1,
    "ZEaFOoEmMrA": 1,
    "Odvtt8gPQ8Q": 1,
    "R-ig8kwTOEI": 1,
    "vNsnl9pM7D8": 1,
    "v59eGHBvZXk": 1,
    "VUtxZL3AThU": 1,
    "yQiuvI3Jwkg": 1,
    "1YUwHYgNwsM": 1,
    "JhHCENYXPk4": 1,
    "EDTxjV1-WXA": 1,
    "tXuaZ-O6OLY": 1,
    "oEhqsvpKVxM": 1,
    "76iN8yBKN8c": 1,
    "_I-DFvtdUTk": 1,
    "f_jUU3Fd3HI": 1,
    "mY2xFxmFpzc": 1,
    "xL1jy5oIm3I": 1,
    "Am2_DkQOZDk": 1,
    "rCoPr8UwRMc": 1,
    "vTr8sgq5oYE": 1,
    "tMHY3yRBSFk": 1,
    "J7ck984Qhso": 1,
    "j3sa8KPye7k": 1,
    "ZRgS_4yPbds": 1,
    "H9d_tQ0Ezys": 1,
    "5FU5j_DvZPg": 1,
    "hFcoj_cIc5E": 1,
    "dPaZNGRcPK4": 1
}